<annotation><folder>/tmp/7152/metadata</folder><filename>Frame00032.jpg</filename><source><database>dummy</database><annotation>dummy</annotation><image>dummy</image><flickrid>dummy</flickrid></source><owner><flickrid>dummy</flickrid><name>dummy</name></owner><size><width>1988</width><height>1326</height><depth>3</depth></size><segmented>0</segmented><object><name>corner</name><pose>dummy</pose><truncated>0</truncated><difficult>0</difficult><bndbox><xmin>316.0</xmin><ymin>1137.0</ymin><xmax>416.0</xmax><ymax>1237.0</ymax></bndbox></object><object><name>corner</name><pose>dummy</pose><truncated>0</truncated><difficult>0</difficult><bndbox><xmin>418.0</xmin><ymin>654.0</ymin><xmax>518.0</xmax><ymax>754.0</ymax></bndbox></object><object><name>corner</name><pose>dummy</pose><truncated>0</truncated><difficult>0</difficult><bndbox><xmin>342.0</xmin><ymin>607.0</ymin><xmax>442.0</xmax><ymax>707.0</ymax></bndbox></object><object><name>corner</name><pose>dummy</pose><truncated>0</truncated><difficult>0</difficult><bndbox><xmin>359.0</xmin><ymin>600.0</ymin><xmax>459.0</xmax><ymax>700.0</ymax></bndbox></object><object><name>corner</name><pose>dummy</pose><truncated>0</truncated><difficult>0</difficult><bndbox><xmin>415.0</xmin><ymin>657.0</ymin><xmax>515.0</xmax><ymax>757.0</ymax></bndbox></object><object><name>corner</name><pose>dummy</pose><truncated>0</truncated><difficult>0</difficult><bndbox><xmin>435.0</xmin><ymin>602.0</ymin><xmax>535.0</xmax><ymax>702.0</ymax></bndbox></object></annotation>