<annotation><folder>/tmp/2451/metadata</folder><filename>Frame00023.jpg</filename><source><database>dummy</database><annotation>dummy</annotation><image>dummy</image><flickrid>dummy</flickrid></source><owner><flickrid>dummy</flickrid><name>dummy</name></owner><size><width>5456</width><height>3632</height><depth>3</depth></size><segmented>0</segmented><object><name>corner</name><pose>dummy</pose><truncated>0</truncated><difficult>0</difficult><bndbox><xmin>3792.36860261</xmin><ymin>582.388618954</ymin><xmax>3892.36860261</xmax><ymax>682.388618954</ymax></bndbox></object><object><name>corner</name><pose>dummy</pose><truncated>0</truncated><difficult>0</difficult><bndbox><xmin>782.34421352</xmin><ymin>1718.67798032</ymin><xmax>882.34421352</xmax><ymax>1818.67798032</ymax></bndbox></object><object><name>corner</name><pose>dummy</pose><truncated>0</truncated><difficult>0</difficult><bndbox><xmin>3816.32486783</xmin><ymin>2110.83580269</ymin><xmax>3916.32486783</xmax><ymax>2210.83580269</ymax></bndbox></object><object><name>corner</name><pose>dummy</pose><truncated>0</truncated><difficult>0</difficult><bndbox><xmin>2794.70966286</xmin><ymin>318.454816711</ymin><xmax>2894.70966286</xmax><ymax>418.454816711</ymax></bndbox></object><object><name>corner</name><pose>dummy</pose><truncated>0</truncated><difficult>0</difficult><bndbox><xmin>3777.77295213</xmin><ymin>35.581817667</ymin><xmax>3877.77295213</xmax><ymax>135.581817667</ymax></bndbox></object></annotation>